{
    "general": {
        "pets": {
            "HohliDog1": ""
        }
    },
    "command": {
        "bughuntersOnline4": "",
        "8ball": {
            "answers": {
                "notsure": ""
            }
        },
        "avatar": {
            "title": ""
        },
        "ping": {
            "pong": ""
        },
        "card": {
            "removecontracttext": ""
        },
        "animals": {
            "randomcat": ""
        },
        "timeout": {
            "noTime": ""
        },
        "leaders": {
            "leadersOfCoinsOnHilarious": ""
        },
        "hit": {
            "noHitYourself": ""
        },
        "help": {
            "page": ""
        },
        "rankcard": {
            "bgsinfo": {
                "default2": ""
            }
        }
    },
    "slashcommand": {
        "bird": {
            "description": ""
        },
        "ben": {
            "description": ""
        }
    }
}
